{
  "_fv": 13,
  "_type": "recipe",
  "definition": {
    "recipeType": "Crafting",
    "xpReward": 0.0,
    "cookingTime": 200,
    "recipeRetstackSize": 1,
    "group": "advanced",
    "recipeShapeless": false,
    "recipeSlots": [
      {
        "value": ""
      },
      {
        "value": "CUSTOM:Adc"
      },
      {
        "value": ""
      },
      {
        "value": "CUSTOM:Adc"
      },
      {
        "value": "CUSTOM:Adc"
      },
      {
        "value": "CUSTOM:Adc"
      },
      {
        "value": ""
      },
      {
        "value": "CUSTOM:Adc"
      },
      {
        "value": ""
      }
    ],
    "recipeReturnStack": {
      "value": "CUSTOM:Tos"
    },
    "name": "tocd",
    "namespace": "mod"
  }
}